fiesta/__init__.py
fiesta/constants.py
fiesta/conversions.py
fiesta/filters.py
fiesta/logging.py
fiesta/plot.py
fiesta/scalers.py
fiesta/utils.py
fiesta/inference/__init__.py
fiesta/inference/fiesta.py
fiesta/inference/injection.py
fiesta/inference/lightcurve_model.py
fiesta/inference/likelihood.py
fiesta/inference/prior.py
fiesta/inference/prior_dict.py
fiesta/inference/systematic.py
fiesta/surrogates/GRB/afgpy_gaussian_CVAE/model/afgpy_gaussian.pkl
fiesta/surrogates/GRB/afgpy_gaussian_CVAE/model/afgpy_gaussian_metadata.pkl
fiesta/surrogates/GRB/afgpy_tophat_CVAE/model/afgpy_tophat.pkl
fiesta/surrogates/GRB/afgpy_tophat_CVAE/model/afgpy_tophat_metadata.pkl
fiesta/surrogates/GRB/pbag_gaussian_CVAE/model/pbag_gaussian.pkl
fiesta/surrogates/GRB/pbag_gaussian_CVAE/model/pbag_gaussian_metadata.pkl
fiesta/surrogates/GRB/pbag_tophat_CVAE/model/pbag_tophat.pkl
fiesta/surrogates/GRB/pbag_tophat_CVAE/model/pbag_tophat_metadata.pkl
fiesta/surrogates/KN/Bu2025_MLP/model/Bu2025_MLP.pkl
fiesta/surrogates/KN/Bu2025_MLP/model/Bu2025_MLP_metadata.pkl
fiesta/train/AfterglowData.py
fiesta/train/Benchmarker.py
fiesta/train/DataManager.py
fiesta/train/FluxTrainer.py
fiesta/train/LightcurveTrainer.py
fiesta/train/__init__.py
fiesta/train/neuralnets.py
fiesta/train/nn_architectures.py
fiestaem-0.1.0.dist-info/licenses/LICENSE
fiestaem-0.1.0.dist-info/METADATA
fiestaem-0.1.0.dist-info/WHEEL
fiestaem-0.1.0.dist-info/top_level.txt
fiestaem-0.1.0.dist-info/RECORD
