Metadata-Version: 2.4
Name: fiestaEM
Version: 0.1.0
Summary: Fast inference of electromagnetic signals with JAX
Author-email: Thibeau Wouters <thibeauwouters@gmail.com>, Hauke Koehn <hauke.koehn@uni-potsdam.de>
License-Expression: MIT
Project-URL: Homepage, https://github.com/nuclear-multimessenger-astronomy/fiestaEM
Keywords: sampling,inference,astrophysics,kilonovae,gamma-ray bursts,afterglow,surrogates
Classifier: Programming Language :: Python
Classifier: Programming Language :: Python :: 3
Requires-Python: >=3.10
License-File: LICENSE
Requires-Dist: dill
Requires-Dist: jax
Requires-Dist: jaxlib
Requires-Dist: flax
Requires-Dist: numpy
Requires-Dist: pandas
Requires-Dist: jaxtyping
Requires-Dist: beartype
Requires-Dist: tqdm
Requires-Dist: scipy
Requires-Dist: ml_collections
Requires-Dist: matplotlib
Requires-Dist: astropy
Requires-Dist: sncosmo
Requires-Dist: flowMC
Requires-Dist: h5py
Requires-Dist: corner
Provides-Extra: grb
Requires-Dist: afterglowpy; extra == "grb"
Provides-Extra: gpu
Requires-Dist: jax[cuda12]; extra == "gpu"
Dynamic: license-file
